holodex/__init__.py
holodex/client.py
holodex/http.py
holodex/model/__init__.py
holodex/model/autocomplete.py
holodex/model/channel.py
holodex/model/channel_video.py
holodex/model/channels.py
holodex/model/live.py
holodex/model/search_comment.py
holodex/model/search_info.py
holodex/model/search_video.py
holodex/model/video.py
tests/__init__.py
tests/conftest.py
tests/test_autocomplete.py
tests/test_channel.py
tests/test_video.py
holodex-0.11.11.dist-info/LICENSE
holodex-0.11.11.dist-info/METADATA
holodex-0.11.11.dist-info/WHEEL
holodex-0.11.11.dist-info/top_level.txt
holodex-0.11.11.dist-info/RECORD
