Metadata-Version: 2.1
Name: holodex
Version: 0.11.11
Summary: Holodex api wrapper
Home-page: https://github.com/ombe1229/holodex
Author: ombe1229
Author-email: h3236516@gmail.com
License: Apache 2.0
License-File: LICENSE
